{
  "unversionedId": "reference/classes/LiquidityMath",
  "id": "version-3.0.0/reference/classes/LiquidityMath",
  "isDocsHomePage": false,
  "title": "LiquidityMath",
  "description": "Methods",
  "source": "@site/SDK_versioned_docs/version-3.0.0/reference/classes/utils_liquiditymath.liquiditymath.md",
  "sourceDirName": "reference/classes",
  "slug": "/reference/classes/LiquidityMath",
  "permalink": "/sdk/reference/classes/LiquidityMath",
  "version": "3.0.0",
  "frontMatter": {
    "id": "LiquidityMath",
    "title": "LiquidityMath"
  },
  "sidebar": "version-V3/sdksidebar",
  "previous": {
    "title": "FullMath",
    "permalink": "/sdk/reference/classes/FullMath"
  },
  "next": {
    "title": "SqrtPriceMath",
    "permalink": "/sdk/reference/classes/SqrtPriceMath"
  }
}